{
	"id": "981f3309-6b44-3f00-ce73-854d409a7f82",
	"name": "springtutorial",
	"description": "",
	"order": [
		"b37abdab-11a3-e2cd-8b40-4d4295ba359e",
		"f7c2c66c-6977-04ae-04c7-aaf26b8c9b75",
		"9a45fbd3-e5d7-5182-19af-410a2b3bf25e",
		"fbe35ec3-5f3b-05b2-5522-ca868c24d3b5"
	],
	"folders": [],
	"timestamp": 1467014054796,
	"owner": 0,
	"remoteLink": "",
	"public": false,
	"published": false,
	"requests": [
		{
			"id": "9a45fbd3-e5d7-5182-19af-410a2b3bf25e",
			"headers": "",
			"url": "http://localhost:8080/login?username=user&password=user",
			"pathVariables": {},
			"preRequestScript": null,
			"method": "POST",
			"collectionId": "981f3309-6b44-3f00-ce73-854d409a7f82",
			"data": null,
			"dataMode": "params",
			"name": "login_user",
			"description": "",
			"descriptionFormat": "html",
			"time": 1467014115073,
			"version": 2,
			"responses": [],
			"tests": null,
			"currentHelper": "normal",
			"helperAttributes": {}
		},
		{
			"id": "b37abdab-11a3-e2cd-8b40-4d4295ba359e",
			"headers": "",
			"url": "http://localhost:8080/login?username=admin&password=admin",
			"pathVariables": {},
			"preRequestScript": null,
			"method": "POST",
			"collectionId": "981f3309-6b44-3f00-ce73-854d409a7f82",
			"data": null,
			"dataMode": "params",
			"name": "login_admin",
			"description": "",
			"descriptionFormat": "html",
			"time": 1467014071971,
			"version": 2,
			"responses": [],
			"tests": null,
			"currentHelper": "normal",
			"helperAttributes": {}
		},
		{
			"id": "f7c2c66c-6977-04ae-04c7-aaf26b8c9b75",
			"headers": "",
			"url": "http://localhost:8080/movies/1",
			"pathVariables": {},
			"preRequestScript": null,
			"method": "GET",
			"collectionId": "981f3309-6b44-3f00-ce73-854d409a7f82",
			"data": null,
			"dataMode": "params",
			"name": "get_movie_1",
			"description": "",
			"descriptionFormat": "html",
			"time": 1467014091497,
			"version": 2,
			"responses": [],
			"tests": null,
			"currentHelper": "normal",
			"helperAttributes": {}
		},
		{
			"id": "fbe35ec3-5f3b-05b2-5522-ca868c24d3b5",
			"headers": "",
			"url": "http://localhost:8080/movies/1?fields=year,director,subject,title",
			"preRequestScript": null,
			"pathVariables": {},
			"method": "GET",
			"data": null,
			"dataMode": "params",
			"version": 2,
			"tests": null,
			"currentHelper": "normal",
			"helperAttributes": {},
			"time": 1467014171741,
			"name": "get_movie_1_fields",
			"description": "",
			"collectionId": "981f3309-6b44-3f00-ce73-854d409a7f82",
			"responses": []
		}
	]
}